generator/__init__.py
generator/doc.py
generator/helper.py
generator/helper_test.py
generator/io.py
generator/model.py
generator/model_template.py
generator/model_test.py
generator/route.py
generator/route_template.py
rest_cli-0.0.3.data/scripts/rest
rest_cli-0.0.3.dist-info/METADATA
rest_cli-0.0.3.dist-info/RECORD
rest_cli-0.0.3.dist-info/WHEEL
rest_cli-0.0.3.dist-info/top_level.txt
