Metadata-Version: 2.1
Name: rest-cli
Version: 0.0.3
Summary: A perfect tool for creating Restful web service in PHP
Home-page: https://github.com/loint/rest-cli
Author: Loi Nguyen
Author-email: loinguyentrung@gmail.com
License: UNKNOWN
Platform: UNKNOWN
Classifier: Programming Language :: Python :: 2
Classifier: License :: OSI Approved :: MIT License
Classifier: Operating System :: OS Independent
Requires-Dist: pytest
Requires-Dist: click
Requires-Dist: mysql-connector-python
